funtool/__init__.py
funtool/convert/__init__.py
funtool/convert/curl2py.py
funtool/crawler/__init__.py
funtool/crawler/ba.py
funtool/crawler/core.py
funtool/crawler/movies.py
funtool/database/__init__.py
funtool/database/core.py
funtool/download/__init__.py
funtool/download/core.py
funtool/download/m3u8.py
funtool/download/story.py
funtool/everything/__init__.py
funtool/everything/d2lzh.py
funtool/load/__init__.py
funtool/load/core.py
funtool/log/__init__.py
funtool/log/log.py
funtool/log/log_widget.py
funtool/math/__init__.py
funtool/math/prime.py
funtool/path/__init__.py
funtool/path/core.py
funtool/secret/__init__.py
funtool/secret/secret.py
funtool/time/__init__.py
funtool/time/core.py
funtool/tool/__init__.py
funtool/tool/build.py
funtool/tool/compress.py
funtool/tool/log.py
funtool/tool/path.py
funtool/tool/pyrss.py
funtool/tool/time.py
funtool/tool/tool.py
funtool/utils/__init__.py
funtool/utils/struct.py
farfuntool-202308221437.dist-info/LICENSE
farfuntool-202308221437.dist-info/METADATA
farfuntool-202308221437.dist-info/WHEEL
farfuntool-202308221437.dist-info/top_level.txt
farfuntool-202308221437.dist-info/RECORD
