Metadata-Version: 2.1
Name: farfuntool
Version: 202308221437
Summary: funtool
Home-page: https://github.com/1007530194
Author: niuliangtao
Author-email: 1007530194@qq.com
License-File: LICENSE
Requires-Dist: cryptography
Requires-Dist: funbuild
